Metadata-Version: 1.1
Name: demultiplex
Version: 1.0.2
Summary: Demultiplex any number of FASTA or a FASTQ files based on a list of barcodes
Home-page: https://github.com/jfjlaros/demultiplex
Author: Jeroen F.J. Laros
Author-email: J.F.J.Laros@lumc.nl
License: MIT
Keywords: bioinformatics
Platform: UNKNOWN
Classifier: Development Status :: 4 - Beta
Classifier: Intended Audience :: Science/Research
Classifier: Intended Audience :: Developers
Classifier: Operating System :: OS Independent
Classifier: Programming Language :: Python
Classifier: Topic :: Scientific/Engineering
